setup.py
gflags_multibool/__init__.py
gflags_multibool/gflags_multibool_test.py
python_gflags_multibool.egg-info/PKG-INFO
python_gflags_multibool.egg-info/SOURCES.txt
python_gflags_multibool.egg-info/dependency_links.txt
python_gflags_multibool.egg-info/requires.txt
python_gflags_multibool.egg-info/top_level.txt
python_gflags_multibool.egg-info/zip-safe