Metadata-Version: 1.0
Name: python-gflags-multibool
Version: 0.0.1
Summary: Python-glags multibooleam extension
Home-page: UNKNOWN
Author: Adam DePrince
Author-email: deprince@googlealumni.com
License: UNKNOWN
Platform: UNKNOWN
